sort_zzk/__init__.py
sort_zzk/sort_zzk.py
sort_zzk-0.0.1.dist-info/LICENSE
sort_zzk-0.0.1.dist-info/METADATA
sort_zzk-0.0.1.dist-info/WHEEL
sort_zzk-0.0.1.dist-info/top_level.txt
sort_zzk-0.0.1.dist-info/RECORD
